{
    "twitch": {
        "identity": {
            "username": "",
            "password": ""
        },
        "connection": {
            "reconnect": true,
            "secure": true
        },
        "channels": [
            ""
        ],
        "Raidminutes": 0
    },
    "useDiscord": true,
    "discord": {
        "token": "",
        "prefix": "!",
        "watchtimechannel": "",
        "evalUsers": [""],
        "channels": {
            "blacklist": "",
            "commands": "",
            "relay": "",
            "adminCommands": ""
        }
    }
}